fsm.py
setup.cfg
setup.py
declarative_fsm.egg-info/PKG-INFO
declarative_fsm.egg-info/SOURCES.txt
declarative_fsm.egg-info/dependency_links.txt
declarative_fsm.egg-info/top_level.txt