Metadata-Version: 1.0
Name: declarative-fsm
Version: 0.0.1
Summary: A Python declarative finite state machine.
Home-page: https://github.com/thomasquintana/declarative-fsm
Author: Thomas Quintana
Author-email: quintana.thomas@gmail.com
License: PROPRIETARY
Platform: UNKNOWN
